symconf/__init__.py
symconf/__main__.py
symconf/config.py
symconf/matching.py
symconf/reader.py
symconf/runner.py
symconf/template.py
symconf/util.py
symconf-0.8.4.dist-info/licenses/LICENSE
symconf-0.8.4.dist-info/METADATA
symconf-0.8.4.dist-info/WHEEL
symconf-0.8.4.dist-info/entry_points.txt
symconf-0.8.4.dist-info/top_level.txt
symconf-0.8.4.dist-info/RECORD
