Metadata-Version: 2.4
Name: symconf
Version: 0.8.4
Summary: Local app configuration manager
Author-email: Sam Griesemer <git@olog.io>
License-Expression: MIT
Project-URL: Homepage, https://doc.olog.io/symconf
Project-URL: Documentation, https://doc.olog.io/symconf
Project-URL: Repository, https://git.olog.io/olog/symconf
Project-URL: Issues, https://git.olog.io/olog/symconf/issues
Keywords: tempate-engine,theme-switcher,configuration-files
Classifier: Programming Language :: Python
Classifier: Operating System :: OS Independent
Classifier: Development Status :: 3 - Alpha
Classifier: Intended Audience :: Developers
Classifier: Intended Audience :: End Users/Desktop
Requires-Python: >=3.12
License-File: LICENSE
Requires-Dist: pyxdg
Requires-Dist: colorama
Provides-Extra: dev
Requires-Dist: ipykernel; extra == "dev"
Provides-Extra: doc
Requires-Dist: sphinx; extra == "doc"
Requires-Dist: sphinx-togglebutton; extra == "doc"
Requires-Dist: sphinx-autodoc-typehints; extra == "doc"
Requires-Dist: furo; extra == "doc"
Requires-Dist: myst-parser; extra == "doc"
Provides-Extra: test
Requires-Dist: pytest; extra == "test"
Dynamic: license-file
